{
    "100039986310453": [
        {
            "type": "message",
            "name": "Nguyễn Duyên Đạt",
            "message": "/ping flop nhé",
            "time": "15/06/2022 22:52:57",
            "attachment": []
        },
        {
            "type": "message",
            "name": "Nguyễn Duyên Đạt",
            "message": "/flop",
            "time": "15/06/2022 22:53:14",
            "attachment": []
        },
        {
            "type": "message",
            "name": "Nguyễn Duyên Đạt",
            "message": "Hmm",
            "time": "15/06/2022 22:53:17",
            "attachment": []
        },
        {
            "type": "message",
            "name": "Nguyễn Duyên Đạt",
            "message": "/flop",
            "time": "15/06/2022 22:53:40",
            "attachment": []
        },
        {
            "type": "message",
            "name": "Nguyễn Duyên Đạt",
            "message": "Mẹ cay thế nhờ=))",
            "time": "15/06/2022 22:53:49",
            "attachment": []
        },
        {
            "type": "message",
            "name": "Nguyễn Duyên Đạt",
            "message": "Bố m xóa tay",
            "time": "15/06/2022 22:53:57",
            "attachment": []
        },
        {
            "type": "message_reply",
            "name": "Nguyễn Duyên Đạt",
            "message": "Chip buồi",
            "time": "15/06/2022 22:54:06",
            "attachment": []
        }
    ],
    "100072563223660": [
        {
            "type": "message",
            "name": "𝑵𝒈𝒖𝒚𝒆𝒏 𝑯𝒖𝒚𝒆𝒏 𝑯𝒂𝒏",
            "message": ":))",
            "time": "15/06/2022 22:52:57",
            "attachment": []
        }
    ],
    "100052992066604": [
        {
            "type": "message_reply",
            "name": "Nguyễn Thị Khánh Huyền",
            "message": "‎‎‎‎‎‎‎‎‎‎‎‎‎‎‎‎flop nhé",
            "time": "15/06/2022 22:52:57",
            "attachment": []
        },
        {
            "type": "message_reply",
            "name": "Nguyễn Thị Khánh Huyền",
            "message": "Quyền Lồn Biên Giới",
            "time": "15/06/2022 22:53:14",
            "attachment": []
        },
        {
            "type": "message",
            "name": "Nguyễn Thị Khánh Huyền",
            "message": "[ Thread Update ] Đã cập nhật người dùng 100052992066604 trở thành quản trị viên nhóm",
            "time": "15/06/2022 22:53:35",
            "attachment": []
        },
        {
            "type": "message_reply",
            "name": "Nguyễn Thị Khánh Huyền",
            "message": "Quyền Lồn Biên Giới",
            "time": "15/06/2022 22:53:41",
            "attachment": []
        },
        {
            "type": "message",
            "name": "Nguyễn Thị Khánh Huyền",
            "message": "",
            "time": "15/06/2022 22:53:50",
            "attachment": [
                {
                    "type": "sticker",
                    "ID": "369239263222822",
                    "url": "https://scontent.xx.fbcdn.net/v/t39.1997-6/39178562_1505197616293642_5411344281094848512_n.png?stp=cp0_dst-png&_nc_cat=1&ccb=1-7&_nc_sid=ac3552&_nc_ohc=ZqJJl5sY9LAAX8q0yfB&_nc_oc=AQnYpO_HxwkaAxojoEPH4v6UOcUlGuFX0sBeoRv_S13PnjbwAXPW-re6iNeX3Kbkolw&_nc_ad=z-m&_nc_cid=0&_nc_ht=scontent.xx&oh=00_AT8koC8ZNi0ZYI5zgwBdCdpxsXDtdK-NWO4e2ieNK77CEQ&oe=62AE1BCB",
                    "packID": "227877430692340",
                    "spriteUrl": null,
                    "spriteUrl2x": null,
                    "width": 72,
                    "height": 72,
                    "caption": "Like, thumbs up",
                    "description": "Like, thumbs up",
                    "frameCount": 1,
                    "frameRate": 83,
                    "framesPerRow": 1,
                    "framesPerCol": 1,
                    "stickerID": "369239263222822",
                    "spriteURI": null,
                    "spriteURI2x": null
                }
            ]
        },
        {
            "type": "message",
            "name": "Nguyễn Thị Khánh Huyền",
            "message": "Gi",
            "time": "15/06/2022 22:53:58",
            "attachment": []
        },
        {
            "type": "message",
            "name": "Nguyễn Thị Khánh Huyền",
            "message": "/flop",
            "time": "15/06/2022 22:54:03",
            "attachment": []
        },
        {
            "type": "message",
            "name": "Nguyễn Thị Khánh Huyền",
            "message": "[ Thread Update ] Đã cập nhật người dùng 100039986310453 trở thành thành viên",
            "time": "15/06/2022 22:54:06",
            "attachment": []
        },
        {
            "type": "message",
            "name": "Nguyễn Thị Khánh Huyền",
            "message": "[ Thread Update ] Đã cập nhật người dùng 100037756460229 trở thành thành viên",
            "time": "15/06/2022 22:54:06",
            "attachment": []
        },
        {
            "type": "message",
            "name": "Nguyễn Thị Khánh Huyền",
            "message": "Gad",
            "time": "15/06/2022 22:54:09",
            "attachment": []
        },
        {
            "type": "message",
            "name": "Nguyễn Thị Khánh Huyền",
            "message": "Hoàng Công Yên Đã bị quản trị viên đá khỏi nhóm",
            "time": "15/06/2022 22:54:09",
            "attachment": [
                {
                    "type": "animated_image",
                    "ID": "5278975228851561",
                    "filename": "gif-5278975228851561",
                    "previewUrl": "https://cdn.fbsbx.com/v/t59.2708-21/271443220_626530735344876_868794249061796397_n.gif?_nc_cat=100&ccb=1-7&_nc_sid=041f46&_nc_ohc=eaScNtbexM0AX95KcvQ&_nc_ht=cdn.fbsbx.com&oh=03_AVIAlJg6gK_VTQyZJamsJ4f1ULvDMvP7RjK8kitwI4O_mQ&oe=62ABD376",
                    "previewWidth": 373,
                    "previewHeight": 444,
                    "url": "https://cdn.fbsbx.com/v/t59.2708-21/271443220_626530735344876_868794249061796397_n.gif?_nc_cat=100&ccb=1-7&_nc_sid=041f46&_nc_ohc=eaScNtbexM0AX95KcvQ&_nc_ht=cdn.fbsbx.com&oh=03_AVIAlJg6gK_VTQyZJamsJ4f1ULvDMvP7RjK8kitwI4O_mQ&oe=62ABD376",
                    "width": 373,
                    "height": 444,
                    "thumbnailUrl": "https://cdn.fbsbx.com/v/t59.2708-21/271443220_626530735344876_868794249061796397_n.gif?_nc_cat=100&ccb=1-7&_nc_sid=041f46&_nc_ohc=eaScNtbexM0AX95KcvQ&_nc_ht=cdn.fbsbx.com&oh=03_AVIAlJg6gK_VTQyZJamsJ4f1ULvDMvP7RjK8kitwI4O_mQ&oe=62ABD376",
                    "name": "gif-5278975228851561",
                    "facebookUrl": "https://cdn.fbsbx.com/v/t59.2708-21/271443220_626530735344876_868794249061796397_n.gif?_nc_cat=100&ccb=1-7&_nc_sid=041f46&_nc_ohc=eaScNtbexM0AX95KcvQ&_nc_ht=cdn.fbsbx.com&oh=03_AVIAlJg6gK_VTQyZJamsJ4f1ULvDMvP7RjK8kitwI4O_mQ&oe=62ABD376",
                    "rawGifImage": "https://cdn.fbsbx.com/v/t59.2708-21/271443220_626530735344876_868794249061796397_n.gif?_nc_cat=100&ccb=1-7&_nc_sid=041f46&_nc_ohc=eaScNtbexM0AX95KcvQ&_nc_ht=cdn.fbsbx.com&oh=03_AVIAlJg6gK_VTQyZJamsJ4f1ULvDMvP7RjK8kitwI4O_mQ&oe=62ABD376",
                    "animatedGifUrl": "https://cdn.fbsbx.com/v/t59.2708-21/271443220_626530735344876_868794249061796397_n.gif?_nc_cat=100&ccb=1-7&_nc_sid=041f46&_nc_ohc=eaScNtbexM0AX95KcvQ&_nc_ht=cdn.fbsbx.com&oh=03_AVIAlJg6gK_VTQyZJamsJ4f1ULvDMvP7RjK8kitwI4O_mQ&oe=62ABD376",
                    "animatedGifPreviewUrl": "https://cdn.fbsbx.com/v/t59.2708-21/271443220_626530735344876_868794249061796397_n.gif?_nc_cat=100&ccb=1-7&_nc_sid=041f46&_nc_ohc=eaScNtbexM0AX95KcvQ&_nc_ht=cdn.fbsbx.com&oh=03_AVIAlJg6gK_VTQyZJamsJ4f1ULvDMvP7RjK8kitwI4O_mQ&oe=62ABD376",
                    "animatedWebpUrl": "https://cdn.fbsbx.com/v/t59.2708-21/271443220_626530735344876_868794249061796397_n.gif?_nc_cat=100&ccb=1-7&_nc_sid=041f46&_nc_ohc=eaScNtbexM0AX95KcvQ&_nc_ht=cdn.fbsbx.com&oh=03_AVIAlJg6gK_VTQyZJamsJ4f1ULvDMvP7RjK8kitwI4O_mQ&oe=62ABD376",
                    "animatedWebpPreviewUrl": "https://cdn.fbsbx.com/v/t59.2708-21/271443220_626530735344876_868794249061796397_n.gif?_nc_cat=100&ccb=1-7&_nc_sid=041f46&_nc_ohc=eaScNtbexM0AX95KcvQ&_nc_ht=cdn.fbsbx.com&oh=03_AVIAlJg6gK_VTQyZJamsJ4f1ULvDMvP7RjK8kitwI4O_mQ&oe=62ABD376"
                }
            ]
        },
        {
            "type": "message",
            "name": "Nguyễn Thị Khánh Huyền",
            "message": "Nguyen Duyen - Dat Đã bị quản trị viên đá khỏi nhóm",
            "time": "15/06/2022 22:54:10",
            "attachment": [
                {
                    "type": "animated_image",
                    "ID": "328898876076874",
                    "filename": "gif-328898876076874",
                    "previewUrl": "https://cdn.fbsbx.com/v/t59.2708-21/271443220_626530735344876_868794249061796397_n.gif?_nc_cat=100&ccb=1-7&_nc_sid=041f46&_nc_ohc=eaScNtbexM0AX95KcvQ&_nc_ht=cdn.fbsbx.com&oh=03_AVIAlJg6gK_VTQyZJamsJ4f1ULvDMvP7RjK8kitwI4O_mQ&oe=62ABD376",
                    "previewWidth": 373,
                    "previewHeight": 444,
                    "url": "https://cdn.fbsbx.com/v/t59.2708-21/271443220_626530735344876_868794249061796397_n.gif?_nc_cat=100&ccb=1-7&_nc_sid=041f46&_nc_ohc=eaScNtbexM0AX95KcvQ&_nc_ht=cdn.fbsbx.com&oh=03_AVIAlJg6gK_VTQyZJamsJ4f1ULvDMvP7RjK8kitwI4O_mQ&oe=62ABD376",
                    "width": 373,
                    "height": 444,
                    "thumbnailUrl": "https://cdn.fbsbx.com/v/t59.2708-21/271443220_626530735344876_868794249061796397_n.gif?_nc_cat=100&ccb=1-7&_nc_sid=041f46&_nc_ohc=eaScNtbexM0AX95KcvQ&_nc_ht=cdn.fbsbx.com&oh=03_AVIAlJg6gK_VTQyZJamsJ4f1ULvDMvP7RjK8kitwI4O_mQ&oe=62ABD376",
                    "name": "gif-328898876076874",
                    "facebookUrl": "https://cdn.fbsbx.com/v/t59.2708-21/271443220_626530735344876_868794249061796397_n.gif?_nc_cat=100&ccb=1-7&_nc_sid=041f46&_nc_ohc=eaScNtbexM0AX95KcvQ&_nc_ht=cdn.fbsbx.com&oh=03_AVIAlJg6gK_VTQyZJamsJ4f1ULvDMvP7RjK8kitwI4O_mQ&oe=62ABD376",
                    "rawGifImage": "https://cdn.fbsbx.com/v/t59.2708-21/271443220_626530735344876_868794249061796397_n.gif?_nc_cat=100&ccb=1-7&_nc_sid=041f46&_nc_ohc=eaScNtbexM0AX95KcvQ&_nc_ht=cdn.fbsbx.com&oh=03_AVIAlJg6gK_VTQyZJamsJ4f1ULvDMvP7RjK8kitwI4O_mQ&oe=62ABD376",
                    "animatedGifUrl": "https://cdn.fbsbx.com/v/t59.2708-21/271443220_626530735344876_868794249061796397_n.gif?_nc_cat=100&ccb=1-7&_nc_sid=041f46&_nc_ohc=eaScNtbexM0AX95KcvQ&_nc_ht=cdn.fbsbx.com&oh=03_AVIAlJg6gK_VTQyZJamsJ4f1ULvDMvP7RjK8kitwI4O_mQ&oe=62ABD376",
                    "animatedGifPreviewUrl": "https://cdn.fbsbx.com/v/t59.2708-21/271443220_626530735344876_868794249061796397_n.gif?_nc_cat=100&ccb=1-7&_nc_sid=041f46&_nc_ohc=eaScNtbexM0AX95KcvQ&_nc_ht=cdn.fbsbx.com&oh=03_AVIAlJg6gK_VTQyZJamsJ4f1ULvDMvP7RjK8kitwI4O_mQ&oe=62ABD376",
                    "animatedWebpUrl": "https://cdn.fbsbx.com/v/t59.2708-21/271443220_626530735344876_868794249061796397_n.gif?_nc_cat=100&ccb=1-7&_nc_sid=041f46&_nc_ohc=eaScNtbexM0AX95KcvQ&_nc_ht=cdn.fbsbx.com&oh=03_AVIAlJg6gK_VTQyZJamsJ4f1ULvDMvP7RjK8kitwI4O_mQ&oe=62ABD376",
                    "animatedWebpPreviewUrl": "https://cdn.fbsbx.com/v/t59.2708-21/271443220_626530735344876_868794249061796397_n.gif?_nc_cat=100&ccb=1-7&_nc_sid=041f46&_nc_ohc=eaScNtbexM0AX95KcvQ&_nc_ht=cdn.fbsbx.com&oh=03_AVIAlJg6gK_VTQyZJamsJ4f1ULvDMvP7RjK8kitwI4O_mQ&oe=62ABD376"
                }
            ]
        },
        {
            "type": "message",
            "name": "Nguyễn Thị Khánh Huyền",
            "message": "Gà",
            "time": "15/06/2022 22:54:11",
            "attachment": []
        },
        {
            "type": "message",
            "name": "Nguyễn Thị Khánh Huyền",
            "message": "Bùi Quang Thái Đã bị quản trị viên đá khỏi nhóm",
            "time": "15/06/2022 22:54:12",
            "attachment": [
                {
                    "type": "animated_image",
                    "ID": "347928467408859",
                    "filename": "gif-347928467408859",
                    "previewUrl": "https://cdn.fbsbx.com/v/t59.2708-21/271443220_626530735344876_868794249061796397_n.gif?_nc_cat=100&ccb=1-7&_nc_sid=041f46&_nc_ohc=eaScNtbexM0AX95KcvQ&_nc_ht=cdn.fbsbx.com&oh=03_AVIAlJg6gK_VTQyZJamsJ4f1ULvDMvP7RjK8kitwI4O_mQ&oe=62ABD376",
                    "previewWidth": 373,
                    "previewHeight": 444,
                    "url": "https://cdn.fbsbx.com/v/t59.2708-21/271443220_626530735344876_868794249061796397_n.gif?_nc_cat=100&ccb=1-7&_nc_sid=041f46&_nc_ohc=eaScNtbexM0AX95KcvQ&_nc_ht=cdn.fbsbx.com&oh=03_AVIAlJg6gK_VTQyZJamsJ4f1ULvDMvP7RjK8kitwI4O_mQ&oe=62ABD376",
                    "width": 373,
                    "height": 444,
                    "thumbnailUrl": "https://cdn.fbsbx.com/v/t59.2708-21/271443220_626530735344876_868794249061796397_n.gif?_nc_cat=100&ccb=1-7&_nc_sid=041f46&_nc_ohc=eaScNtbexM0AX95KcvQ&_nc_ht=cdn.fbsbx.com&oh=03_AVIAlJg6gK_VTQyZJamsJ4f1ULvDMvP7RjK8kitwI4O_mQ&oe=62ABD376",
                    "name": "gif-347928467408859",
                    "facebookUrl": "https://cdn.fbsbx.com/v/t59.2708-21/271443220_626530735344876_868794249061796397_n.gif?_nc_cat=100&ccb=1-7&_nc_sid=041f46&_nc_ohc=eaScNtbexM0AX95KcvQ&_nc_ht=cdn.fbsbx.com&oh=03_AVIAlJg6gK_VTQyZJamsJ4f1ULvDMvP7RjK8kitwI4O_mQ&oe=62ABD376",
                    "rawGifImage": "https://cdn.fbsbx.com/v/t59.2708-21/271443220_626530735344876_868794249061796397_n.gif?_nc_cat=100&ccb=1-7&_nc_sid=041f46&_nc_ohc=eaScNtbexM0AX95KcvQ&_nc_ht=cdn.fbsbx.com&oh=03_AVIAlJg6gK_VTQyZJamsJ4f1ULvDMvP7RjK8kitwI4O_mQ&oe=62ABD376",
                    "animatedGifUrl": "https://cdn.fbsbx.com/v/t59.2708-21/271443220_626530735344876_868794249061796397_n.gif?_nc_cat=100&ccb=1-7&_nc_sid=041f46&_nc_ohc=eaScNtbexM0AX95KcvQ&_nc_ht=cdn.fbsbx.com&oh=03_AVIAlJg6gK_VTQyZJamsJ4f1ULvDMvP7RjK8kitwI4O_mQ&oe=62ABD376",
                    "animatedGifPreviewUrl": "https://cdn.fbsbx.com/v/t59.2708-21/271443220_626530735344876_868794249061796397_n.gif?_nc_cat=100&ccb=1-7&_nc_sid=041f46&_nc_ohc=eaScNtbexM0AX95KcvQ&_nc_ht=cdn.fbsbx.com&oh=03_AVIAlJg6gK_VTQyZJamsJ4f1ULvDMvP7RjK8kitwI4O_mQ&oe=62ABD376",
                    "animatedWebpUrl": "https://cdn.fbsbx.com/v/t59.2708-21/271443220_626530735344876_868794249061796397_n.gif?_nc_cat=100&ccb=1-7&_nc_sid=041f46&_nc_ohc=eaScNtbexM0AX95KcvQ&_nc_ht=cdn.fbsbx.com&oh=03_AVIAlJg6gK_VTQyZJamsJ4f1ULvDMvP7RjK8kitwI4O_mQ&oe=62ABD376",
                    "animatedWebpPreviewUrl": "https://cdn.fbsbx.com/v/t59.2708-21/271443220_626530735344876_868794249061796397_n.gif?_nc_cat=100&ccb=1-7&_nc_sid=041f46&_nc_ohc=eaScNtbexM0AX95KcvQ&_nc_ht=cdn.fbsbx.com&oh=03_AVIAlJg6gK_VTQyZJamsJ4f1ULvDMvP7RjK8kitwI4O_mQ&oe=62ABD376"
                }
            ]
        },
        {
            "type": "message",
            "name": "Nguyễn Thị Khánh Huyền",
            "message": "Dăng Ok Đã bị quản trị viên đá khỏi nhóm",
            "time": "15/06/2022 22:54:12",
            "attachment": [
                {
                    "type": "animated_image",
                    "ID": "416623927141780",
                    "filename": "gif-416623927141780",
                    "previewUrl": "https://cdn.fbsbx.com/v/t59.2708-21/271443220_626530735344876_868794249061796397_n.gif?_nc_cat=100&ccb=1-7&_nc_sid=041f46&_nc_ohc=eaScNtbexM0AX95KcvQ&_nc_ht=cdn.fbsbx.com&oh=03_AVIAlJg6gK_VTQyZJamsJ4f1ULvDMvP7RjK8kitwI4O_mQ&oe=62ABD376",
                    "previewWidth": 373,
                    "previewHeight": 444,
                    "url": "https://cdn.fbsbx.com/v/t59.2708-21/271443220_626530735344876_868794249061796397_n.gif?_nc_cat=100&ccb=1-7&_nc_sid=041f46&_nc_ohc=eaScNtbexM0AX95KcvQ&_nc_ht=cdn.fbsbx.com&oh=03_AVIAlJg6gK_VTQyZJamsJ4f1ULvDMvP7RjK8kitwI4O_mQ&oe=62ABD376",
                    "width": 373,
                    "height": 444,
                    "thumbnailUrl": "https://cdn.fbsbx.com/v/t59.2708-21/271443220_626530735344876_868794249061796397_n.gif?_nc_cat=100&ccb=1-7&_nc_sid=041f46&_nc_ohc=eaScNtbexM0AX95KcvQ&_nc_ht=cdn.fbsbx.com&oh=03_AVIAlJg6gK_VTQyZJamsJ4f1ULvDMvP7RjK8kitwI4O_mQ&oe=62ABD376",
                    "name": "gif-416623927141780",
                    "facebookUrl": "https://cdn.fbsbx.com/v/t59.2708-21/271443220_626530735344876_868794249061796397_n.gif?_nc_cat=100&ccb=1-7&_nc_sid=041f46&_nc_ohc=eaScNtbexM0AX95KcvQ&_nc_ht=cdn.fbsbx.com&oh=03_AVIAlJg6gK_VTQyZJamsJ4f1ULvDMvP7RjK8kitwI4O_mQ&oe=62ABD376",
                    "rawGifImage": "https://cdn.fbsbx.com/v/t59.2708-21/271443220_626530735344876_868794249061796397_n.gif?_nc_cat=100&ccb=1-7&_nc_sid=041f46&_nc_ohc=eaScNtbexM0AX95KcvQ&_nc_ht=cdn.fbsbx.com&oh=03_AVIAlJg6gK_VTQyZJamsJ4f1ULvDMvP7RjK8kitwI4O_mQ&oe=62ABD376",
                    "animatedGifUrl": "https://cdn.fbsbx.com/v/t59.2708-21/271443220_626530735344876_868794249061796397_n.gif?_nc_cat=100&ccb=1-7&_nc_sid=041f46&_nc_ohc=eaScNtbexM0AX95KcvQ&_nc_ht=cdn.fbsbx.com&oh=03_AVIAlJg6gK_VTQyZJamsJ4f1ULvDMvP7RjK8kitwI4O_mQ&oe=62ABD376",
                    "animatedGifPreviewUrl": "https://cdn.fbsbx.com/v/t59.2708-21/271443220_626530735344876_868794249061796397_n.gif?_nc_cat=100&ccb=1-7&_nc_sid=041f46&_nc_ohc=eaScNtbexM0AX95KcvQ&_nc_ht=cdn.fbsbx.com&oh=03_AVIAlJg6gK_VTQyZJamsJ4f1ULvDMvP7RjK8kitwI4O_mQ&oe=62ABD376",
                    "animatedWebpUrl": "https://cdn.fbsbx.com/v/t59.2708-21/271443220_626530735344876_868794249061796397_n.gif?_nc_cat=100&ccb=1-7&_nc_sid=041f46&_nc_ohc=eaScNtbexM0AX95KcvQ&_nc_ht=cdn.fbsbx.com&oh=03_AVIAlJg6gK_VTQyZJamsJ4f1ULvDMvP7RjK8kitwI4O_mQ&oe=62ABD376",
                    "animatedWebpPreviewUrl": "https://cdn.fbsbx.com/v/t59.2708-21/271443220_626530735344876_868794249061796397_n.gif?_nc_cat=100&ccb=1-7&_nc_sid=041f46&_nc_ohc=eaScNtbexM0AX95KcvQ&_nc_ht=cdn.fbsbx.com&oh=03_AVIAlJg6gK_VTQyZJamsJ4f1ULvDMvP7RjK8kitwI4O_mQ&oe=62ABD376"
                }
            ]
        },
        {
            "type": "message",
            "name": "Nguyễn Thị Khánh Huyền",
            "message": "Nguyễn Huy Hoàng Đã bị quản trị viên đá khỏi nhóm",
            "time": "15/06/2022 22:54:13",
            "attachment": [
                {
                    "type": "animated_image",
                    "ID": "1178402612937741",
                    "filename": "gif-1178402612937741",
                    "previewUrl": "https://cdn.fbsbx.com/v/t59.2708-21/271443220_626530735344876_868794249061796397_n.gif?_nc_cat=100&ccb=1-7&_nc_sid=041f46&_nc_ohc=eaScNtbexM0AX95KcvQ&_nc_ht=cdn.fbsbx.com&oh=03_AVIAlJg6gK_VTQyZJamsJ4f1ULvDMvP7RjK8kitwI4O_mQ&oe=62ABD376",
                    "previewWidth": 373,
                    "previewHeight": 444,
                    "url": "https://cdn.fbsbx.com/v/t59.2708-21/271443220_626530735344876_868794249061796397_n.gif?_nc_cat=100&ccb=1-7&_nc_sid=041f46&_nc_ohc=eaScNtbexM0AX95KcvQ&_nc_ht=cdn.fbsbx.com&oh=03_AVIAlJg6gK_VTQyZJamsJ4f1ULvDMvP7RjK8kitwI4O_mQ&oe=62ABD376",
                    "width": 373,
                    "height": 444,
                    "thumbnailUrl": "https://cdn.fbsbx.com/v/t59.2708-21/271443220_626530735344876_868794249061796397_n.gif?_nc_cat=100&ccb=1-7&_nc_sid=041f46&_nc_ohc=eaScNtbexM0AX95KcvQ&_nc_ht=cdn.fbsbx.com&oh=03_AVIAlJg6gK_VTQyZJamsJ4f1ULvDMvP7RjK8kitwI4O_mQ&oe=62ABD376",
                    "name": "gif-1178402612937741",
                    "facebookUrl": "https://cdn.fbsbx.com/v/t59.2708-21/271443220_626530735344876_868794249061796397_n.gif?_nc_cat=100&ccb=1-7&_nc_sid=041f46&_nc_ohc=eaScNtbexM0AX95KcvQ&_nc_ht=cdn.fbsbx.com&oh=03_AVIAlJg6gK_VTQyZJamsJ4f1ULvDMvP7RjK8kitwI4O_mQ&oe=62ABD376",
                    "rawGifImage": "https://cdn.fbsbx.com/v/t59.2708-21/271443220_626530735344876_868794249061796397_n.gif?_nc_cat=100&ccb=1-7&_nc_sid=041f46&_nc_ohc=eaScNtbexM0AX95KcvQ&_nc_ht=cdn.fbsbx.com&oh=03_AVIAlJg6gK_VTQyZJamsJ4f1ULvDMvP7RjK8kitwI4O_mQ&oe=62ABD376",
                    "animatedGifUrl": "https://cdn.fbsbx.com/v/t59.2708-21/271443220_626530735344876_868794249061796397_n.gif?_nc_cat=100&ccb=1-7&_nc_sid=041f46&_nc_ohc=eaScNtbexM0AX95KcvQ&_nc_ht=cdn.fbsbx.com&oh=03_AVIAlJg6gK_VTQyZJamsJ4f1ULvDMvP7RjK8kitwI4O_mQ&oe=62ABD376",
                    "animatedGifPreviewUrl": "https://cdn.fbsbx.com/v/t59.2708-21/271443220_626530735344876_868794249061796397_n.gif?_nc_cat=100&ccb=1-7&_nc_sid=041f46&_nc_ohc=eaScNtbexM0AX95KcvQ&_nc_ht=cdn.fbsbx.com&oh=03_AVIAlJg6gK_VTQyZJamsJ4f1ULvDMvP7RjK8kitwI4O_mQ&oe=62ABD376",
                    "animatedWebpUrl": "https://cdn.fbsbx.com/v/t59.2708-21/271443220_626530735344876_868794249061796397_n.gif?_nc_cat=100&ccb=1-7&_nc_sid=041f46&_nc_ohc=eaScNtbexM0AX95KcvQ&_nc_ht=cdn.fbsbx.com&oh=03_AVIAlJg6gK_VTQyZJamsJ4f1ULvDMvP7RjK8kitwI4O_mQ&oe=62ABD376",
                    "animatedWebpPreviewUrl": "https://cdn.fbsbx.com/v/t59.2708-21/271443220_626530735344876_868794249061796397_n.gif?_nc_cat=100&ccb=1-7&_nc_sid=041f46&_nc_ohc=eaScNtbexM0AX95KcvQ&_nc_ht=cdn.fbsbx.com&oh=03_AVIAlJg6gK_VTQyZJamsJ4f1ULvDMvP7RjK8kitwI4O_mQ&oe=62ABD376"
                }
            ]
        },
        {
            "type": "message",
            "name": "Nguyễn Thị Khánh Huyền",
            "message": "Nguyễn Duyên Đạt Đã bị quản trị viên đá khỏi nhóm",
            "time": "15/06/2022 22:54:14",
            "attachment": [
                {
                    "type": "animated_image",
                    "ID": "1082551929048478",
                    "filename": "gif-1082551929048478",
                    "previewUrl": "https://cdn.fbsbx.com/v/t59.2708-21/271443220_626530735344876_868794249061796397_n.gif?_nc_cat=100&ccb=1-7&_nc_sid=041f46&_nc_ohc=eaScNtbexM0AX95KcvQ&_nc_ht=cdn.fbsbx.com&oh=03_AVIAlJg6gK_VTQyZJamsJ4f1ULvDMvP7RjK8kitwI4O_mQ&oe=62ABD376",
                    "previewWidth": 373,
                    "previewHeight": 444,
                    "url": "https://cdn.fbsbx.com/v/t59.2708-21/271443220_626530735344876_868794249061796397_n.gif?_nc_cat=100&ccb=1-7&_nc_sid=041f46&_nc_ohc=eaScNtbexM0AX95KcvQ&_nc_ht=cdn.fbsbx.com&oh=03_AVIAlJg6gK_VTQyZJamsJ4f1ULvDMvP7RjK8kitwI4O_mQ&oe=62ABD376",
                    "width": 373,
                    "height": 444,
                    "thumbnailUrl": "https://cdn.fbsbx.com/v/t59.2708-21/271443220_626530735344876_868794249061796397_n.gif?_nc_cat=100&ccb=1-7&_nc_sid=041f46&_nc_ohc=eaScNtbexM0AX95KcvQ&_nc_ht=cdn.fbsbx.com&oh=03_AVIAlJg6gK_VTQyZJamsJ4f1ULvDMvP7RjK8kitwI4O_mQ&oe=62ABD376",
                    "name": "gif-1082551929048478",
                    "facebookUrl": "https://cdn.fbsbx.com/v/t59.2708-21/271443220_626530735344876_868794249061796397_n.gif?_nc_cat=100&ccb=1-7&_nc_sid=041f46&_nc_ohc=eaScNtbexM0AX95KcvQ&_nc_ht=cdn.fbsbx.com&oh=03_AVIAlJg6gK_VTQyZJamsJ4f1ULvDMvP7RjK8kitwI4O_mQ&oe=62ABD376",
                    "rawGifImage": "https://cdn.fbsbx.com/v/t59.2708-21/271443220_626530735344876_868794249061796397_n.gif?_nc_cat=100&ccb=1-7&_nc_sid=041f46&_nc_ohc=eaScNtbexM0AX95KcvQ&_nc_ht=cdn.fbsbx.com&oh=03_AVIAlJg6gK_VTQyZJamsJ4f1ULvDMvP7RjK8kitwI4O_mQ&oe=62ABD376",
                    "animatedGifUrl": "https://cdn.fbsbx.com/v/t59.2708-21/271443220_626530735344876_868794249061796397_n.gif?_nc_cat=100&ccb=1-7&_nc_sid=041f46&_nc_ohc=eaScNtbexM0AX95KcvQ&_nc_ht=cdn.fbsbx.com&oh=03_AVIAlJg6gK_VTQyZJamsJ4f1ULvDMvP7RjK8kitwI4O_mQ&oe=62ABD376",
                    "animatedGifPreviewUrl": "https://cdn.fbsbx.com/v/t59.2708-21/271443220_626530735344876_868794249061796397_n.gif?_nc_cat=100&ccb=1-7&_nc_sid=041f46&_nc_ohc=eaScNtbexM0AX95KcvQ&_nc_ht=cdn.fbsbx.com&oh=03_AVIAlJg6gK_VTQyZJamsJ4f1ULvDMvP7RjK8kitwI4O_mQ&oe=62ABD376",
                    "animatedWebpUrl": "https://cdn.fbsbx.com/v/t59.2708-21/271443220_626530735344876_868794249061796397_n.gif?_nc_cat=100&ccb=1-7&_nc_sid=041f46&_nc_ohc=eaScNtbexM0AX95KcvQ&_nc_ht=cdn.fbsbx.com&oh=03_AVIAlJg6gK_VTQyZJamsJ4f1ULvDMvP7RjK8kitwI4O_mQ&oe=62ABD376",
                    "animatedWebpPreviewUrl": "https://cdn.fbsbx.com/v/t59.2708-21/271443220_626530735344876_868794249061796397_n.gif?_nc_cat=100&ccb=1-7&_nc_sid=041f46&_nc_ohc=eaScNtbexM0AX95KcvQ&_nc_ht=cdn.fbsbx.com&oh=03_AVIAlJg6gK_VTQyZJamsJ4f1ULvDMvP7RjK8kitwI4O_mQ&oe=62ABD376"
                }
            ]
        },
        {
            "type": "message",
            "name": "Nguyễn Thị Khánh Huyền",
            "message": "Vo Trong Quan Đã bị quản trị viên đá khỏi nhóm",
            "time": "15/06/2022 22:54:17",
            "attachment": [
                {
                    "type": "animated_image",
                    "ID": "3119920498259271",
                    "filename": "gif-3119920498259271",
                    "previewUrl": "https://cdn.fbsbx.com/v/t59.2708-21/271443220_626530735344876_868794249061796397_n.gif?_nc_cat=100&ccb=1-7&_nc_sid=041f46&_nc_ohc=eaScNtbexM0AX95KcvQ&_nc_ht=cdn.fbsbx.com&oh=03_AVIAlJg6gK_VTQyZJamsJ4f1ULvDMvP7RjK8kitwI4O_mQ&oe=62ABD376",
                    "previewWidth": 373,
                    "previewHeight": 444,
                    "url": "https://cdn.fbsbx.com/v/t59.2708-21/271443220_626530735344876_868794249061796397_n.gif?_nc_cat=100&ccb=1-7&_nc_sid=041f46&_nc_ohc=eaScNtbexM0AX95KcvQ&_nc_ht=cdn.fbsbx.com&oh=03_AVIAlJg6gK_VTQyZJamsJ4f1ULvDMvP7RjK8kitwI4O_mQ&oe=62ABD376",
                    "width": 373,
                    "height": 444,
                    "thumbnailUrl": "https://cdn.fbsbx.com/v/t59.2708-21/271443220_626530735344876_868794249061796397_n.gif?_nc_cat=100&ccb=1-7&_nc_sid=041f46&_nc_ohc=eaScNtbexM0AX95KcvQ&_nc_ht=cdn.fbsbx.com&oh=03_AVIAlJg6gK_VTQyZJamsJ4f1ULvDMvP7RjK8kitwI4O_mQ&oe=62ABD376",
                    "name": "gif-3119920498259271",
                    "facebookUrl": "https://cdn.fbsbx.com/v/t59.2708-21/271443220_626530735344876_868794249061796397_n.gif?_nc_cat=100&ccb=1-7&_nc_sid=041f46&_nc_ohc=eaScNtbexM0AX95KcvQ&_nc_ht=cdn.fbsbx.com&oh=03_AVIAlJg6gK_VTQyZJamsJ4f1ULvDMvP7RjK8kitwI4O_mQ&oe=62ABD376",
                    "rawGifImage": "https://cdn.fbsbx.com/v/t59.2708-21/271443220_626530735344876_868794249061796397_n.gif?_nc_cat=100&ccb=1-7&_nc_sid=041f46&_nc_ohc=eaScNtbexM0AX95KcvQ&_nc_ht=cdn.fbsbx.com&oh=03_AVIAlJg6gK_VTQyZJamsJ4f1ULvDMvP7RjK8kitwI4O_mQ&oe=62ABD376",
                    "animatedGifUrl": "https://cdn.fbsbx.com/v/t59.2708-21/271443220_626530735344876_868794249061796397_n.gif?_nc_cat=100&ccb=1-7&_nc_sid=041f46&_nc_ohc=eaScNtbexM0AX95KcvQ&_nc_ht=cdn.fbsbx.com&oh=03_AVIAlJg6gK_VTQyZJamsJ4f1ULvDMvP7RjK8kitwI4O_mQ&oe=62ABD376",
                    "animatedGifPreviewUrl": "https://cdn.fbsbx.com/v/t59.2708-21/271443220_626530735344876_868794249061796397_n.gif?_nc_cat=100&ccb=1-7&_nc_sid=041f46&_nc_ohc=eaScNtbexM0AX95KcvQ&_nc_ht=cdn.fbsbx.com&oh=03_AVIAlJg6gK_VTQyZJamsJ4f1ULvDMvP7RjK8kitwI4O_mQ&oe=62ABD376",
                    "animatedWebpUrl": "https://cdn.fbsbx.com/v/t59.2708-21/271443220_626530735344876_868794249061796397_n.gif?_nc_cat=100&ccb=1-7&_nc_sid=041f46&_nc_ohc=eaScNtbexM0AX95KcvQ&_nc_ht=cdn.fbsbx.com&oh=03_AVIAlJg6gK_VTQyZJamsJ4f1ULvDMvP7RjK8kitwI4O_mQ&oe=62ABD376",
                    "animatedWebpPreviewUrl": "https://cdn.fbsbx.com/v/t59.2708-21/271443220_626530735344876_868794249061796397_n.gif?_nc_cat=100&ccb=1-7&_nc_sid=041f46&_nc_ohc=eaScNtbexM0AX95KcvQ&_nc_ht=cdn.fbsbx.com&oh=03_AVIAlJg6gK_VTQyZJamsJ4f1ULvDMvP7RjK8kitwI4O_mQ&oe=62ABD376"
                }
            ]
        },
        {
            "type": "message",
            "name": "Nguyễn Thị Khánh Huyền",
            "message": "Quân Lê Đã bị quản trị viên đá khỏi nhóm",
            "time": "15/06/2022 22:54:17",
            "attachment": [
                {
                    "type": "animated_image",
                    "ID": "433660642098259",
                    "filename": "gif-433660642098259",
                    "previewUrl": "https://cdn.fbsbx.com/v/t59.2708-21/271443220_626530735344876_868794249061796397_n.gif?_nc_cat=100&ccb=1-7&_nc_sid=041f46&_nc_ohc=eaScNtbexM0AX95KcvQ&_nc_ht=cdn.fbsbx.com&oh=03_AVIAlJg6gK_VTQyZJamsJ4f1ULvDMvP7RjK8kitwI4O_mQ&oe=62ABD376",
                    "previewWidth": 373,
                    "previewHeight": 444,
                    "url": "https://cdn.fbsbx.com/v/t59.2708-21/271443220_626530735344876_868794249061796397_n.gif?_nc_cat=100&ccb=1-7&_nc_sid=041f46&_nc_ohc=eaScNtbexM0AX95KcvQ&_nc_ht=cdn.fbsbx.com&oh=03_AVIAlJg6gK_VTQyZJamsJ4f1ULvDMvP7RjK8kitwI4O_mQ&oe=62ABD376",
                    "width": 373,
                    "height": 444,
                    "thumbnailUrl": "https://cdn.fbsbx.com/v/t59.2708-21/271443220_626530735344876_868794249061796397_n.gif?_nc_cat=100&ccb=1-7&_nc_sid=041f46&_nc_ohc=eaScNtbexM0AX95KcvQ&_nc_ht=cdn.fbsbx.com&oh=03_AVIAlJg6gK_VTQyZJamsJ4f1ULvDMvP7RjK8kitwI4O_mQ&oe=62ABD376",
                    "name": "gif-433660642098259",
                    "facebookUrl": "https://cdn.fbsbx.com/v/t59.2708-21/271443220_626530735344876_868794249061796397_n.gif?_nc_cat=100&ccb=1-7&_nc_sid=041f46&_nc_ohc=eaScNtbexM0AX95KcvQ&_nc_ht=cdn.fbsbx.com&oh=03_AVIAlJg6gK_VTQyZJamsJ4f1ULvDMvP7RjK8kitwI4O_mQ&oe=62ABD376",
                    "rawGifImage": "https://cdn.fbsbx.com/v/t59.2708-21/271443220_626530735344876_868794249061796397_n.gif?_nc_cat=100&ccb=1-7&_nc_sid=041f46&_nc_ohc=eaScNtbexM0AX95KcvQ&_nc_ht=cdn.fbsbx.com&oh=03_AVIAlJg6gK_VTQyZJamsJ4f1ULvDMvP7RjK8kitwI4O_mQ&oe=62ABD376",
                    "animatedGifUrl": "https://cdn.fbsbx.com/v/t59.2708-21/271443220_626530735344876_868794249061796397_n.gif?_nc_cat=100&ccb=1-7&_nc_sid=041f46&_nc_ohc=eaScNtbexM0AX95KcvQ&_nc_ht=cdn.fbsbx.com&oh=03_AVIAlJg6gK_VTQyZJamsJ4f1ULvDMvP7RjK8kitwI4O_mQ&oe=62ABD376",
                    "animatedGifPreviewUrl": "https://cdn.fbsbx.com/v/t59.2708-21/271443220_626530735344876_868794249061796397_n.gif?_nc_cat=100&ccb=1-7&_nc_sid=041f46&_nc_ohc=eaScNtbexM0AX95KcvQ&_nc_ht=cdn.fbsbx.com&oh=03_AVIAlJg6gK_VTQyZJamsJ4f1ULvDMvP7RjK8kitwI4O_mQ&oe=62ABD376",
                    "animatedWebpUrl": "https://cdn.fbsbx.com/v/t59.2708-21/271443220_626530735344876_868794249061796397_n.gif?_nc_cat=100&ccb=1-7&_nc_sid=041f46&_nc_ohc=eaScNtbexM0AX95KcvQ&_nc_ht=cdn.fbsbx.com&oh=03_AVIAlJg6gK_VTQyZJamsJ4f1ULvDMvP7RjK8kitwI4O_mQ&oe=62ABD376",
                    "animatedWebpPreviewUrl": "https://cdn.fbsbx.com/v/t59.2708-21/271443220_626530735344876_868794249061796397_n.gif?_nc_cat=100&ccb=1-7&_nc_sid=041f46&_nc_ohc=eaScNtbexM0AX95KcvQ&_nc_ht=cdn.fbsbx.com&oh=03_AVIAlJg6gK_VTQyZJamsJ4f1ULvDMvP7RjK8kitwI4O_mQ&oe=62ABD376"
                }
            ]
        },
        {
            "type": "message",
            "name": "Nguyễn Thị Khánh Huyền",
            "message": "Ngọc Huy Đã bị quản trị viên đá khỏi nhóm",
            "time": "15/06/2022 22:54:18",
            "attachment": [
                {
                    "type": "animated_image",
                    "ID": "553349386297206",
                    "filename": "gif-553349386297206",
                    "previewUrl": "https://cdn.fbsbx.com/v/t59.2708-21/271443220_626530735344876_868794249061796397_n.gif?_nc_cat=100&ccb=1-7&_nc_sid=041f46&_nc_ohc=eaScNtbexM0AX95KcvQ&_nc_ht=cdn.fbsbx.com&oh=03_AVIAlJg6gK_VTQyZJamsJ4f1ULvDMvP7RjK8kitwI4O_mQ&oe=62ABD376",
                    "previewWidth": 373,
                    "previewHeight": 444,
                    "url": "https://cdn.fbsbx.com/v/t59.2708-21/271443220_626530735344876_868794249061796397_n.gif?_nc_cat=100&ccb=1-7&_nc_sid=041f46&_nc_ohc=eaScNtbexM0AX95KcvQ&_nc_ht=cdn.fbsbx.com&oh=03_AVIAlJg6gK_VTQyZJamsJ4f1ULvDMvP7RjK8kitwI4O_mQ&oe=62ABD376",
                    "width": 373,
                    "height": 444,
                    "thumbnailUrl": "https://cdn.fbsbx.com/v/t59.2708-21/271443220_626530735344876_868794249061796397_n.gif?_nc_cat=100&ccb=1-7&_nc_sid=041f46&_nc_ohc=eaScNtbexM0AX95KcvQ&_nc_ht=cdn.fbsbx.com&oh=03_AVIAlJg6gK_VTQyZJamsJ4f1ULvDMvP7RjK8kitwI4O_mQ&oe=62ABD376",
                    "name": "gif-553349386297206",
                    "facebookUrl": "https://cdn.fbsbx.com/v/t59.2708-21/271443220_626530735344876_868794249061796397_n.gif?_nc_cat=100&ccb=1-7&_nc_sid=041f46&_nc_ohc=eaScNtbexM0AX95KcvQ&_nc_ht=cdn.fbsbx.com&oh=03_AVIAlJg6gK_VTQyZJamsJ4f1ULvDMvP7RjK8kitwI4O_mQ&oe=62ABD376",
                    "rawGifImage": "https://cdn.fbsbx.com/v/t59.2708-21/271443220_626530735344876_868794249061796397_n.gif?_nc_cat=100&ccb=1-7&_nc_sid=041f46&_nc_ohc=eaScNtbexM0AX95KcvQ&_nc_ht=cdn.fbsbx.com&oh=03_AVIAlJg6gK_VTQyZJamsJ4f1ULvDMvP7RjK8kitwI4O_mQ&oe=62ABD376",
                    "animatedGifUrl": "https://cdn.fbsbx.com/v/t59.2708-21/271443220_626530735344876_868794249061796397_n.gif?_nc_cat=100&ccb=1-7&_nc_sid=041f46&_nc_ohc=eaScNtbexM0AX95KcvQ&_nc_ht=cdn.fbsbx.com&oh=03_AVIAlJg6gK_VTQyZJamsJ4f1ULvDMvP7RjK8kitwI4O_mQ&oe=62ABD376",
                    "animatedGifPreviewUrl": "https://cdn.fbsbx.com/v/t59.2708-21/271443220_626530735344876_868794249061796397_n.gif?_nc_cat=100&ccb=1-7&_nc_sid=041f46&_nc_ohc=eaScNtbexM0AX95KcvQ&_nc_ht=cdn.fbsbx.com&oh=03_AVIAlJg6gK_VTQyZJamsJ4f1ULvDMvP7RjK8kitwI4O_mQ&oe=62ABD376",
                    "animatedWebpUrl": "https://cdn.fbsbx.com/v/t59.2708-21/271443220_626530735344876_868794249061796397_n.gif?_nc_cat=100&ccb=1-7&_nc_sid=041f46&_nc_ohc=eaScNtbexM0AX95KcvQ&_nc_ht=cdn.fbsbx.com&oh=03_AVIAlJg6gK_VTQyZJamsJ4f1ULvDMvP7RjK8kitwI4O_mQ&oe=62ABD376",
                    "animatedWebpPreviewUrl": "https://cdn.fbsbx.com/v/t59.2708-21/271443220_626530735344876_868794249061796397_n.gif?_nc_cat=100&ccb=1-7&_nc_sid=041f46&_nc_ohc=eaScNtbexM0AX95KcvQ&_nc_ht=cdn.fbsbx.com&oh=03_AVIAlJg6gK_VTQyZJamsJ4f1ULvDMvP7RjK8kitwI4O_mQ&oe=62ABD376"
                }
            ]
        },
        {
            "type": "message",
            "name": "Nguyễn Thị Khánh Huyền",
            "message": "Nguyen Anh Thư Đã bị quản trị viên đá khỏi nhóm",
            "time": "15/06/2022 22:54:20",
            "attachment": [
                {
                    "type": "animated_image",
                    "ID": "757773138758448",
                    "filename": "gif-757773138758448",
                    "previewUrl": "https://cdn.fbsbx.com/v/t59.2708-21/271443220_626530735344876_868794249061796397_n.gif?_nc_cat=100&ccb=1-7&_nc_sid=041f46&_nc_ohc=eaScNtbexM0AX95KcvQ&_nc_ht=cdn.fbsbx.com&oh=03_AVIAlJg6gK_VTQyZJamsJ4f1ULvDMvP7RjK8kitwI4O_mQ&oe=62ABD376",
                    "previewWidth": 373,
                    "previewHeight": 444,
                    "url": "https://cdn.fbsbx.com/v/t59.2708-21/271443220_626530735344876_868794249061796397_n.gif?_nc_cat=100&ccb=1-7&_nc_sid=041f46&_nc_ohc=eaScNtbexM0AX95KcvQ&_nc_ht=cdn.fbsbx.com&oh=03_AVIAlJg6gK_VTQyZJamsJ4f1ULvDMvP7RjK8kitwI4O_mQ&oe=62ABD376",
                    "width": 373,
                    "height": 444,
                    "thumbnailUrl": "https://cdn.fbsbx.com/v/t59.2708-21/271443220_626530735344876_868794249061796397_n.gif?_nc_cat=100&ccb=1-7&_nc_sid=041f46&_nc_ohc=eaScNtbexM0AX95KcvQ&_nc_ht=cdn.fbsbx.com&oh=03_AVIAlJg6gK_VTQyZJamsJ4f1ULvDMvP7RjK8kitwI4O_mQ&oe=62ABD376",
                    "name": "gif-757773138758448",
                    "facebookUrl": "https://cdn.fbsbx.com/v/t59.2708-21/271443220_626530735344876_868794249061796397_n.gif?_nc_cat=100&ccb=1-7&_nc_sid=041f46&_nc_ohc=eaScNtbexM0AX95KcvQ&_nc_ht=cdn.fbsbx.com&oh=03_AVIAlJg6gK_VTQyZJamsJ4f1ULvDMvP7RjK8kitwI4O_mQ&oe=62ABD376",
                    "rawGifImage": "https://cdn.fbsbx.com/v/t59.2708-21/271443220_626530735344876_868794249061796397_n.gif?_nc_cat=100&ccb=1-7&_nc_sid=041f46&_nc_ohc=eaScNtbexM0AX95KcvQ&_nc_ht=cdn.fbsbx.com&oh=03_AVIAlJg6gK_VTQyZJamsJ4f1ULvDMvP7RjK8kitwI4O_mQ&oe=62ABD376",
                    "animatedGifUrl": "https://cdn.fbsbx.com/v/t59.2708-21/271443220_626530735344876_868794249061796397_n.gif?_nc_cat=100&ccb=1-7&_nc_sid=041f46&_nc_ohc=eaScNtbexM0AX95KcvQ&_nc_ht=cdn.fbsbx.com&oh=03_AVIAlJg6gK_VTQyZJamsJ4f1ULvDMvP7RjK8kitwI4O_mQ&oe=62ABD376",
                    "animatedGifPreviewUrl": "https://cdn.fbsbx.com/v/t59.2708-21/271443220_626530735344876_868794249061796397_n.gif?_nc_cat=100&ccb=1-7&_nc_sid=041f46&_nc_ohc=eaScNtbexM0AX95KcvQ&_nc_ht=cdn.fbsbx.com&oh=03_AVIAlJg6gK_VTQyZJamsJ4f1ULvDMvP7RjK8kitwI4O_mQ&oe=62ABD376",
                    "animatedWebpUrl": "https://cdn.fbsbx.com/v/t59.2708-21/271443220_626530735344876_868794249061796397_n.gif?_nc_cat=100&ccb=1-7&_nc_sid=041f46&_nc_ohc=eaScNtbexM0AX95KcvQ&_nc_ht=cdn.fbsbx.com&oh=03_AVIAlJg6gK_VTQyZJamsJ4f1ULvDMvP7RjK8kitwI4O_mQ&oe=62ABD376",
                    "animatedWebpPreviewUrl": "https://cdn.fbsbx.com/v/t59.2708-21/271443220_626530735344876_868794249061796397_n.gif?_nc_cat=100&ccb=1-7&_nc_sid=041f46&_nc_ohc=eaScNtbexM0AX95KcvQ&_nc_ht=cdn.fbsbx.com&oh=03_AVIAlJg6gK_VTQyZJamsJ4f1ULvDMvP7RjK8kitwI4O_mQ&oe=62ABD376"
                }
            ]
        },
        {
            "type": "message",
            "name": "Nguyễn Thị Khánh Huyền",
            "message": "𝑵𝒈𝒖𝒚𝒆𝒏 𝑯𝒖𝒚𝒆𝒏 𝑯𝒂𝒏 Đã bị quản trị viên đá khỏi nhóm",
            "time": "15/06/2022 22:54:21",
            "attachment": [
                {
                    "type": "animated_image",
                    "ID": "2158334890996614",
                    "filename": "gif-2158334890996614",
                    "previewUrl": "https://cdn.fbsbx.com/v/t59.2708-21/271443220_626530735344876_868794249061796397_n.gif?_nc_cat=100&ccb=1-7&_nc_sid=041f46&_nc_ohc=eaScNtbexM0AX95KcvQ&_nc_ht=cdn.fbsbx.com&oh=03_AVIAlJg6gK_VTQyZJamsJ4f1ULvDMvP7RjK8kitwI4O_mQ&oe=62ABD376",
                    "previewWidth": 373,
                    "previewHeight": 444,
                    "url": "https://cdn.fbsbx.com/v/t59.2708-21/271443220_626530735344876_868794249061796397_n.gif?_nc_cat=100&ccb=1-7&_nc_sid=041f46&_nc_ohc=eaScNtbexM0AX95KcvQ&_nc_ht=cdn.fbsbx.com&oh=03_AVIAlJg6gK_VTQyZJamsJ4f1ULvDMvP7RjK8kitwI4O_mQ&oe=62ABD376",
                    "width": 373,
                    "height": 444,
                    "thumbnailUrl": "https://cdn.fbsbx.com/v/t59.2708-21/271443220_626530735344876_868794249061796397_n.gif?_nc_cat=100&ccb=1-7&_nc_sid=041f46&_nc_ohc=eaScNtbexM0AX95KcvQ&_nc_ht=cdn.fbsbx.com&oh=03_AVIAlJg6gK_VTQyZJamsJ4f1ULvDMvP7RjK8kitwI4O_mQ&oe=62ABD376",
                    "name": "gif-2158334890996614",
                    "facebookUrl": "https://cdn.fbsbx.com/v/t59.2708-21/271443220_626530735344876_868794249061796397_n.gif?_nc_cat=100&ccb=1-7&_nc_sid=041f46&_nc_ohc=eaScNtbexM0AX95KcvQ&_nc_ht=cdn.fbsbx.com&oh=03_AVIAlJg6gK_VTQyZJamsJ4f1ULvDMvP7RjK8kitwI4O_mQ&oe=62ABD376",
                    "rawGifImage": "https://cdn.fbsbx.com/v/t59.2708-21/271443220_626530735344876_868794249061796397_n.gif?_nc_cat=100&ccb=1-7&_nc_sid=041f46&_nc_ohc=eaScNtbexM0AX95KcvQ&_nc_ht=cdn.fbsbx.com&oh=03_AVIAlJg6gK_VTQyZJamsJ4f1ULvDMvP7RjK8kitwI4O_mQ&oe=62ABD376",
                    "animatedGifUrl": "https://cdn.fbsbx.com/v/t59.2708-21/271443220_626530735344876_868794249061796397_n.gif?_nc_cat=100&ccb=1-7&_nc_sid=041f46&_nc_ohc=eaScNtbexM0AX95KcvQ&_nc_ht=cdn.fbsbx.com&oh=03_AVIAlJg6gK_VTQyZJamsJ4f1ULvDMvP7RjK8kitwI4O_mQ&oe=62ABD376",
                    "animatedGifPreviewUrl": "https://cdn.fbsbx.com/v/t59.2708-21/271443220_626530735344876_868794249061796397_n.gif?_nc_cat=100&ccb=1-7&_nc_sid=041f46&_nc_ohc=eaScNtbexM0AX95KcvQ&_nc_ht=cdn.fbsbx.com&oh=03_AVIAlJg6gK_VTQyZJamsJ4f1ULvDMvP7RjK8kitwI4O_mQ&oe=62ABD376",
                    "animatedWebpUrl": "https://cdn.fbsbx.com/v/t59.2708-21/271443220_626530735344876_868794249061796397_n.gif?_nc_cat=100&ccb=1-7&_nc_sid=041f46&_nc_ohc=eaScNtbexM0AX95KcvQ&_nc_ht=cdn.fbsbx.com&oh=03_AVIAlJg6gK_VTQyZJamsJ4f1ULvDMvP7RjK8kitwI4O_mQ&oe=62ABD376",
                    "animatedWebpPreviewUrl": "https://cdn.fbsbx.com/v/t59.2708-21/271443220_626530735344876_868794249061796397_n.gif?_nc_cat=100&ccb=1-7&_nc_sid=041f46&_nc_ohc=eaScNtbexM0AX95KcvQ&_nc_ht=cdn.fbsbx.com&oh=03_AVIAlJg6gK_VTQyZJamsJ4f1ULvDMvP7RjK8kitwI4O_mQ&oe=62ABD376"
                }
            ]
        },
        {
            "type": "message",
            "name": "Nguyễn Thị Khánh Huyền",
            "message": "NGUYEN NGOC ANH Đã bị quản trị viên đá khỏi nhóm",
            "time": "15/06/2022 22:54:22",
            "attachment": [
                {
                    "type": "animated_image",
                    "ID": "984830112179144",
                    "filename": "gif-984830112179144",
                    "previewUrl": "https://cdn.fbsbx.com/v/t59.2708-21/271443220_626530735344876_868794249061796397_n.gif?_nc_cat=100&ccb=1-7&_nc_sid=041f46&_nc_ohc=eaScNtbexM0AX95KcvQ&_nc_ht=cdn.fbsbx.com&oh=03_AVIAlJg6gK_VTQyZJamsJ4f1ULvDMvP7RjK8kitwI4O_mQ&oe=62ABD376",
                    "previewWidth": 373,
                    "previewHeight": 444,
                    "url": "https://cdn.fbsbx.com/v/t59.2708-21/271443220_626530735344876_868794249061796397_n.gif?_nc_cat=100&ccb=1-7&_nc_sid=041f46&_nc_ohc=eaScNtbexM0AX95KcvQ&_nc_ht=cdn.fbsbx.com&oh=03_AVIAlJg6gK_VTQyZJamsJ4f1ULvDMvP7RjK8kitwI4O_mQ&oe=62ABD376",
                    "width": 373,
                    "height": 444,
                    "thumbnailUrl": "https://cdn.fbsbx.com/v/t59.2708-21/271443220_626530735344876_868794249061796397_n.gif?_nc_cat=100&ccb=1-7&_nc_sid=041f46&_nc_ohc=eaScNtbexM0AX95KcvQ&_nc_ht=cdn.fbsbx.com&oh=03_AVIAlJg6gK_VTQyZJamsJ4f1ULvDMvP7RjK8kitwI4O_mQ&oe=62ABD376",
                    "name": "gif-984830112179144",
                    "facebookUrl": "https://cdn.fbsbx.com/v/t59.2708-21/271443220_626530735344876_868794249061796397_n.gif?_nc_cat=100&ccb=1-7&_nc_sid=041f46&_nc_ohc=eaScNtbexM0AX95KcvQ&_nc_ht=cdn.fbsbx.com&oh=03_AVIAlJg6gK_VTQyZJamsJ4f1ULvDMvP7RjK8kitwI4O_mQ&oe=62ABD376",
                    "rawGifImage": "https://cdn.fbsbx.com/v/t59.2708-21/271443220_626530735344876_868794249061796397_n.gif?_nc_cat=100&ccb=1-7&_nc_sid=041f46&_nc_ohc=eaScNtbexM0AX95KcvQ&_nc_ht=cdn.fbsbx.com&oh=03_AVIAlJg6gK_VTQyZJamsJ4f1ULvDMvP7RjK8kitwI4O_mQ&oe=62ABD376",
                    "animatedGifUrl": "https://cdn.fbsbx.com/v/t59.2708-21/271443220_626530735344876_868794249061796397_n.gif?_nc_cat=100&ccb=1-7&_nc_sid=041f46&_nc_ohc=eaScNtbexM0AX95KcvQ&_nc_ht=cdn.fbsbx.com&oh=03_AVIAlJg6gK_VTQyZJamsJ4f1ULvDMvP7RjK8kitwI4O_mQ&oe=62ABD376",
                    "animatedGifPreviewUrl": "https://cdn.fbsbx.com/v/t59.2708-21/271443220_626530735344876_868794249061796397_n.gif?_nc_cat=100&ccb=1-7&_nc_sid=041f46&_nc_ohc=eaScNtbexM0AX95KcvQ&_nc_ht=cdn.fbsbx.com&oh=03_AVIAlJg6gK_VTQyZJamsJ4f1ULvDMvP7RjK8kitwI4O_mQ&oe=62ABD376",
                    "animatedWebpUrl": "https://cdn.fbsbx.com/v/t59.2708-21/271443220_626530735344876_868794249061796397_n.gif?_nc_cat=100&ccb=1-7&_nc_sid=041f46&_nc_ohc=eaScNtbexM0AX95KcvQ&_nc_ht=cdn.fbsbx.com&oh=03_AVIAlJg6gK_VTQyZJamsJ4f1ULvDMvP7RjK8kitwI4O_mQ&oe=62ABD376",
                    "animatedWebpPreviewUrl": "https://cdn.fbsbx.com/v/t59.2708-21/271443220_626530735344876_868794249061796397_n.gif?_nc_cat=100&ccb=1-7&_nc_sid=041f46&_nc_ohc=eaScNtbexM0AX95KcvQ&_nc_ht=cdn.fbsbx.com&oh=03_AVIAlJg6gK_VTQyZJamsJ4f1ULvDMvP7RjK8kitwI4O_mQ&oe=62ABD376"
                }
            ]
        },
        {
            "type": "message",
            "name": "Nguyễn Thị Khánh Huyền",
            "message": "[ Thread Update ] Đã cập nhật tên nhóm thành Ahihi Đồ Ngốc🤪🤪",
            "time": "15/06/2022 22:54:22",
            "attachment": []
        },
        {
            "type": "message",
            "name": "Nguyễn Thị Khánh Huyền",
            "message": "Ngoc Anh Đã bị quản trị viên đá khỏi nhóm",
            "time": "15/06/2022 22:54:25",
            "attachment": [
                {
                    "type": "animated_image",
                    "ID": "1731718740510194",
                    "filename": "gif-1731718740510194",
                    "previewUrl": "https://cdn.fbsbx.com/v/t59.2708-21/271443220_626530735344876_868794249061796397_n.gif?_nc_cat=100&ccb=1-7&_nc_sid=041f46&_nc_ohc=eaScNtbexM0AX95KcvQ&_nc_ht=cdn.fbsbx.com&oh=03_AVIAlJg6gK_VTQyZJamsJ4f1ULvDMvP7RjK8kitwI4O_mQ&oe=62ABD376",
                    "previewWidth": 373,
                    "previewHeight": 444,
                    "url": "https://cdn.fbsbx.com/v/t59.2708-21/271443220_626530735344876_868794249061796397_n.gif?_nc_cat=100&ccb=1-7&_nc_sid=041f46&_nc_ohc=eaScNtbexM0AX95KcvQ&_nc_ht=cdn.fbsbx.com&oh=03_AVIAlJg6gK_VTQyZJamsJ4f1ULvDMvP7RjK8kitwI4O_mQ&oe=62ABD376",
                    "width": 373,
                    "height": 444,
                    "thumbnailUrl": "https://cdn.fbsbx.com/v/t59.2708-21/271443220_626530735344876_868794249061796397_n.gif?_nc_cat=100&ccb=1-7&_nc_sid=041f46&_nc_ohc=eaScNtbexM0AX95KcvQ&_nc_ht=cdn.fbsbx.com&oh=03_AVIAlJg6gK_VTQyZJamsJ4f1ULvDMvP7RjK8kitwI4O_mQ&oe=62ABD376",
                    "name": "gif-1731718740510194",
                    "facebookUrl": "https://cdn.fbsbx.com/v/t59.2708-21/271443220_626530735344876_868794249061796397_n.gif?_nc_cat=100&ccb=1-7&_nc_sid=041f46&_nc_ohc=eaScNtbexM0AX95KcvQ&_nc_ht=cdn.fbsbx.com&oh=03_AVIAlJg6gK_VTQyZJamsJ4f1ULvDMvP7RjK8kitwI4O_mQ&oe=62ABD376",
                    "rawGifImage": "https://cdn.fbsbx.com/v/t59.2708-21/271443220_626530735344876_868794249061796397_n.gif?_nc_cat=100&ccb=1-7&_nc_sid=041f46&_nc_ohc=eaScNtbexM0AX95KcvQ&_nc_ht=cdn.fbsbx.com&oh=03_AVIAlJg6gK_VTQyZJamsJ4f1ULvDMvP7RjK8kitwI4O_mQ&oe=62ABD376",
                    "animatedGifUrl": "https://cdn.fbsbx.com/v/t59.2708-21/271443220_626530735344876_868794249061796397_n.gif?_nc_cat=100&ccb=1-7&_nc_sid=041f46&_nc_ohc=eaScNtbexM0AX95KcvQ&_nc_ht=cdn.fbsbx.com&oh=03_AVIAlJg6gK_VTQyZJamsJ4f1ULvDMvP7RjK8kitwI4O_mQ&oe=62ABD376",
                    "animatedGifPreviewUrl": "https://cdn.fbsbx.com/v/t59.2708-21/271443220_626530735344876_868794249061796397_n.gif?_nc_cat=100&ccb=1-7&_nc_sid=041f46&_nc_ohc=eaScNtbexM0AX95KcvQ&_nc_ht=cdn.fbsbx.com&oh=03_AVIAlJg6gK_VTQyZJamsJ4f1ULvDMvP7RjK8kitwI4O_mQ&oe=62ABD376",
                    "animatedWebpUrl": "https://cdn.fbsbx.com/v/t59.2708-21/271443220_626530735344876_868794249061796397_n.gif?_nc_cat=100&ccb=1-7&_nc_sid=041f46&_nc_ohc=eaScNtbexM0AX95KcvQ&_nc_ht=cdn.fbsbx.com&oh=03_AVIAlJg6gK_VTQyZJamsJ4f1ULvDMvP7RjK8kitwI4O_mQ&oe=62ABD376",
                    "animatedWebpPreviewUrl": "https://cdn.fbsbx.com/v/t59.2708-21/271443220_626530735344876_868794249061796397_n.gif?_nc_cat=100&ccb=1-7&_nc_sid=041f46&_nc_ohc=eaScNtbexM0AX95KcvQ&_nc_ht=cdn.fbsbx.com&oh=03_AVIAlJg6gK_VTQyZJamsJ4f1ULvDMvP7RjK8kitwI4O_mQ&oe=62ABD376"
                }
            ]
        },
        {
            "type": "message",
            "name": "Nguyễn Thị Khánh Huyền",
            "message": "Hân Huyền Đã bị quản trị viên đá khỏi nhóm",
            "time": "15/06/2022 22:54:25",
            "attachment": [
                {
                    "type": "animated_image",
                    "ID": "419723636828276",
                    "filename": "gif-419723636828276",
                    "previewUrl": "https://cdn.fbsbx.com/v/t59.2708-21/271443220_626530735344876_868794249061796397_n.gif?_nc_cat=100&ccb=1-7&_nc_sid=041f46&_nc_ohc=eaScNtbexM0AX95KcvQ&_nc_ht=cdn.fbsbx.com&oh=03_AVIAlJg6gK_VTQyZJamsJ4f1ULvDMvP7RjK8kitwI4O_mQ&oe=62ABD376",
                    "previewWidth": 373,
                    "previewHeight": 444,
                    "url": "https://cdn.fbsbx.com/v/t59.2708-21/271443220_626530735344876_868794249061796397_n.gif?_nc_cat=100&ccb=1-7&_nc_sid=041f46&_nc_ohc=eaScNtbexM0AX95KcvQ&_nc_ht=cdn.fbsbx.com&oh=03_AVIAlJg6gK_VTQyZJamsJ4f1ULvDMvP7RjK8kitwI4O_mQ&oe=62ABD376",
                    "width": 373,
                    "height": 444,
                    "thumbnailUrl": "https://cdn.fbsbx.com/v/t59.2708-21/271443220_626530735344876_868794249061796397_n.gif?_nc_cat=100&ccb=1-7&_nc_sid=041f46&_nc_ohc=eaScNtbexM0AX95KcvQ&_nc_ht=cdn.fbsbx.com&oh=03_AVIAlJg6gK_VTQyZJamsJ4f1ULvDMvP7RjK8kitwI4O_mQ&oe=62ABD376",
                    "name": "gif-419723636828276",
                    "facebookUrl": "https://cdn.fbsbx.com/v/t59.2708-21/271443220_626530735344876_868794249061796397_n.gif?_nc_cat=100&ccb=1-7&_nc_sid=041f46&_nc_ohc=eaScNtbexM0AX95KcvQ&_nc_ht=cdn.fbsbx.com&oh=03_AVIAlJg6gK_VTQyZJamsJ4f1ULvDMvP7RjK8kitwI4O_mQ&oe=62ABD376",
                    "rawGifImage": "https://cdn.fbsbx.com/v/t59.2708-21/271443220_626530735344876_868794249061796397_n.gif?_nc_cat=100&ccb=1-7&_nc_sid=041f46&_nc_ohc=eaScNtbexM0AX95KcvQ&_nc_ht=cdn.fbsbx.com&oh=03_AVIAlJg6gK_VTQyZJamsJ4f1ULvDMvP7RjK8kitwI4O_mQ&oe=62ABD376",
                    "animatedGifUrl": "https://cdn.fbsbx.com/v/t59.2708-21/271443220_626530735344876_868794249061796397_n.gif?_nc_cat=100&ccb=1-7&_nc_sid=041f46&_nc_ohc=eaScNtbexM0AX95KcvQ&_nc_ht=cdn.fbsbx.com&oh=03_AVIAlJg6gK_VTQyZJamsJ4f1ULvDMvP7RjK8kitwI4O_mQ&oe=62ABD376",
                    "animatedGifPreviewUrl": "https://cdn.fbsbx.com/v/t59.2708-21/271443220_626530735344876_868794249061796397_n.gif?_nc_cat=100&ccb=1-7&_nc_sid=041f46&_nc_ohc=eaScNtbexM0AX95KcvQ&_nc_ht=cdn.fbsbx.com&oh=03_AVIAlJg6gK_VTQyZJamsJ4f1ULvDMvP7RjK8kitwI4O_mQ&oe=62ABD376",
                    "animatedWebpUrl": "https://cdn.fbsbx.com/v/t59.2708-21/271443220_626530735344876_868794249061796397_n.gif?_nc_cat=100&ccb=1-7&_nc_sid=041f46&_nc_ohc=eaScNtbexM0AX95KcvQ&_nc_ht=cdn.fbsbx.com&oh=03_AVIAlJg6gK_VTQyZJamsJ4f1ULvDMvP7RjK8kitwI4O_mQ&oe=62ABD376",
                    "animatedWebpPreviewUrl": "https://cdn.fbsbx.com/v/t59.2708-21/271443220_626530735344876_868794249061796397_n.gif?_nc_cat=100&ccb=1-7&_nc_sid=041f46&_nc_ohc=eaScNtbexM0AX95KcvQ&_nc_ht=cdn.fbsbx.com&oh=03_AVIAlJg6gK_VTQyZJamsJ4f1ULvDMvP7RjK8kitwI4O_mQ&oe=62ABD376"
                }
            ]
        },
        {
            "type": "message",
            "name": "Nguyễn Thị Khánh Huyền",
            "message": "» THÔNG BÁO TỪ ADMIN BOT «\n\nnhận viết báo pr bản thân 20k 1 bài",
            "time": "17/06/2022 18:27:49",
            "attachment": []
        },
        {
            "type": "message",
            "name": "Nguyễn Thị Khánh Huyền",
            "message": "» THÔNG BÁO TỪ ADMIN BOT «\n\nnhận viết báo pr bản thân 20k1 bài | ib cho admin xem demo",
            "time": "18/06/2022 13:29:46",
            "attachment": []
        },
        {
            "type": "message",
            "name": "Nguyễn Thị Khánh Huyền",
            "message": "» THÔNG BÁO TỪ ADMIN BOT «\n\n956 anh còn k unlock đc \nLàm sao anh unlock khoá quần em",
            "time": "22/06/2022 13:07:50",
            "attachment": []
        },
        {
            "type": "message",
            "name": "Nguyễn Thị Khánh Huyền",
            "message": "Bot out",
            "time": "22/06/2022 16:43:15",
            "attachment": []
        },
        {
            "type": "message",
            "name": "Nguyễn Thị Khánh Huyền",
            "message": "Tạm biệt mng ><",
            "time": "22/06/2022 16:43:15",
            "attachment": []
        }
    ],
    "100043862587931": [
        {
            "type": "message_reply",
            "name": "Vo Trong Quan",
            "message": "Thằng nào mà ngu vậy",
            "time": "15/06/2022 22:53:54",
            "attachment": []
        }
    ]
}